[
  {
    "CdsFCBContext": "{\"FileType\":true,\"ImageExternalStorage\":true}",
    "EntitySetName": "mpa_groups",
    "IsHidden": false,
    "IsSampleData": false,
    "IsWritable": true,
    "LogicalName": "mpa_group",
    "MaxGetRowsCount": 500,
    "Name": "Groups",
    "NativeCDSDataSourceInfoNameMapping": {
      "_ownerid_value": "Owner",
      "createdby": "Created By",
      "createdon": "Created On",
      "createdonbehalfby": "Created By (Delegate)",
      "importsequencenumber": "Import Sequence Number",
      "modifiedby": "Modified By",
      "modifiedon": "Modified On",
      "modifiedonbehalfby": "Modified By (Delegate)",
      "mpa_group_AsyncOperations": "System Jobs",
      "mpa_group_BulkDeleteFailures": "Bulk Delete Failures",
      "mpa_group_DuplicateBaseRecord": "Duplicate Records (mpa_group_DuplicateBaseRecord)",
      "mpa_group_DuplicateMatchingRecord": "Duplicate Records (mpa_group_DuplicateMatchingRecord)",
      "mpa_group_MailboxTrackingFolders": "Mailbox Auto Tracking Folders",
      "mpa_group_PrincipalObjectAttributeAccesses": "Field Sharing",
      "mpa_group_ProcessSession": "Process Sessions",
      "mpa_group_SyncErrors": "Sync Errors",
      "mpa_groupid": "Group",
      "mpa_groupmember_groupid_mpa_group": "Group Members",
      "mpa_name": "Name",
      "mpa_nomination_groupid_mpa_group": "Nominations",
      "overriddencreatedon": "Record Created On",
      "owningbusinessunit": "Owning Business Unit",
      "owningteam": "Owning Team",
      "owninguser": "Owning User",
      "statecode": "Status",
      "statuscode": "Status Reason",
      "timezoneruleversionnumber": "Time Zone Rule Version Number",
      "utcconversiontimezonecode": "UTC Conversion Time Zone Code",
      "versionnumber": "Version Number"
    },
    "PreferredName": "Groups",
    "Type": "NativeCDSDataSourceInfo"
  },
  {
    "DisplayName": "Groups (Views)",
    "Name": "_mpa_group_views",
    "RelatedEntityName": "Groups",
    "TrimmedViewName": true,
    "Type": "ViewInfo",
    "ViewInfoNameMapping": {
      "3fc87f01-8926-41b8-9327-957ed955fca0": "Inactive Groups",
      "47d434ce-d0f7-469d-b28b-343877b69417": "Group Advanced Find View",
      "4bdd6e4b-3eed-48ab-b6db-6b1c5b93b82e": "Group Associated View",
      "a45474c6-d752-46ac-b08a-40cfb893e565": "Active Groups",
      "f9dd0bf1-4c82-4e2e-a44a-a8e244e748da": "Group Lookup View"
    }
  },
  {
    "DisplayName": "Status (Groups)",
    "Name": "mpa_group_statecode",
    "OptionSetInfoNameMapping": {
      "0": "Active",
      "1": "Inactive"
    },
    "OptionSetIsBooleanValued": false,
    "OptionSetIsGlobal": false,
    "OptionSetReference": {
      "OptionSetReferenceItem0": {
        "OptionSetReferenceColumnName": "statecode",
        "OptionSetReferenceEntityName": "Groups"
      }
    },
    "OptionSetTypeKey": "StateType",
    "RelatedColumnInvariantName": "statecode",
    "RelatedEntityName": "Groups",
    "Type": "OptionSetInfo"
  },
  {
    "DisplayName": "Status Reason (Groups)",
    "Name": "mpa_group_statuscode",
    "OptionSetInfoNameMapping": {
      "1": "Active",
      "2": "Inactive"
    },
    "OptionSetIsBooleanValued": false,
    "OptionSetIsGlobal": false,
    "OptionSetReference": {
      "OptionSetReferenceItem0": {
        "OptionSetReferenceColumnName": "statuscode",
        "OptionSetReferenceEntityName": "Groups"
      }
    },
    "OptionSetTypeKey": "StatusType",
    "RelatedColumnInvariantName": "statuscode",
    "RelatedEntityName": "Groups",
    "Type": "OptionSetInfo"
  }
]