<?xml version="1.0" encoding="utf-8"?>
<savedqueries xmlns:xsi="http://www.w3.org/2001/XMLSchema-instance">
  <savedquery>
    <IsCustomizable>1</IsCustomizable>
    <CanBeDeleted>0</CanBeDeleted>
    <isquickfindquery>0</isquickfindquery>
    <isprivate>0</isprivate>
    <isdefault>1</isdefault>
    <savedqueryid>{7325acd2-3a3d-4871-b95e-ee430142d5a6}</savedqueryid>
    <layoutxml>
      <grid name="mpa_installprocessstages" jump="mpa_name" select="1" icon="1" preview="0">
        <row name="mpa_installprocessstage" id="mpa_installprocessstageid">
          <cell name="mpa_name" width="300" />
          <cell name="mpa_installprocess" width="122" />
        </row>
      </grid>
    </layoutxml>
    <querytype>64</querytype>
    <fetchxml>
      <fetch version="1.0" mapping="logical">
        <entity name="mpa_installprocessstage">
          <attribute name="mpa_installprocessstageid" />
          <attribute name="mpa_name" />
          <filter type="and">
            <condition attribute="statecode" operator="eq" value="0" />
          </filter>
          <attribute name="mpa_installprocess" />
          <order attribute="mpa_installprocess" descending="false" />
          <order attribute="mpa_name" descending="false" />
        </entity>
      </fetch>
    </fetchxml>
    <IntroducedVersion>1.0</IntroducedVersion>
    <LocalizedNames>
      <LocalizedName description="Install Process Stage Lookup View" languagecode="1033" />
    </LocalizedNames>
  </savedquery>
</savedqueries>