<?xml version="1.0" encoding="utf-8"?>
<EntityRelationships xmlns:xsi="http://www.w3.org/2001/XMLSchema-instance">
  <EntityRelationship Name="business_unit_mpa_iterror" />
  <EntityRelationship Name="business_unit_mpa_itlocalization" />
  <EntityRelationship Name="lk_mpa_iterror_createdby" />
  <EntityRelationship Name="lk_mpa_iterror_modifiedby" />
  <EntityRelationship Name="lk_mpa_itlocalization_createdby" />
  <EntityRelationship Name="lk_mpa_itlocalization_modifiedby" />
  <EntityRelationship Name="owner_mpa_iterror" />
  <EntityRelationship Name="owner_mpa_itlocalization" />
  <EntityRelationship Name="team_mpa_iterror" />
  <EntityRelationship Name="team_mpa_itlocalization" />
  <EntityRelationship Name="user_mpa_iterror" />
  <EntityRelationship Name="user_mpa_itlocalization" />
</EntityRelationships>