{
  "ComponentAllowCustomization": true,
  "ComponentChangedSinceFileImport": false,
  "ComponentManifest": {
    "AllowAccessToGlobals": true,
    "AllowCustomization": true,
    "Description": "",
    "Name": "MaterialSearch",
    "TemplateGuid": "f69a75a6dad0417eae43e297c90ad1a4"
  },
  "ComponentType": "CanvasComponent",
  "CustomGroupControlTemplateName": "",
  "CustomProperties": [
    {
      "Category": 0,
      "DisplayName": "ResetSearch",
      "Hidden": false,
      "IsResettable": true,
      "Name": "ResetSearch",
      "PropertyDataTypeKey": "Boolean",
      "Tooltip": "A custom property",
      "Type": "{\"Version\":\"1.334\",\"Type\":{\"Name\":\"Root\",\"Kind\":\"Boolean\",\"EnumString\":\"\",\"Type\":[]}}"
    }
  ],
  "FirstParty": true,
  "Id": "http://microsoft.com/appmagic/Component",
  "IsComponentLocked": false,
  "IsComponentTemplate": true,
  "IsCustomGroupControlTemplate": false,
  "IsPcfControl": false,
  "IsPremiumPcfControl": false,
  "IsWidgetTemplate": false,
  "LastModifiedTimestamp": "638267549907841803",
  "Name": "f69a75a6dad0417eae43e297c90ad1a4",
  "OverridableProperties": {},
  "TemplateOriginalName": "058aee3ab3f84299a99e6fea8e1d87f0",
  "Version": "638144336178162507"
}