{
  "362c4cb3-5166-4138-b723-445c14f85649": {
    "appActions": [],
    "connectionRef": {
      "apiTier": "Premium",
      "bypassConsent": true,
      "displayName": "Microsoft Dataverse",
      "iconUri": "https://connectoricons-prod.azureedge.net/releases/v1.0.1716/1.0.1716.3922/commondataserviceforapps/icon.png",
      "id": "/providers/microsoft.powerapps/apis/shared_commondataserviceforapps",
      "parameterHints": {},
      "parameterHintsV2": {}
    },
    "datasets": {},
    "dataSources": [],
    "dependencies": {},
    "dependents": [
      "5da627cb-7ece-4c8a-8780-c2391ae7939d"
    ],
    "id": "362c4cb3-5166-4138-b723-445c14f85649"
  },
  "5afad8e3-abb9-4f2d-b8b5-fdb2e81b1583": {
    "appActions": [
      "MyProfile_V2"
    ],
    "connectionRef": {
      "apiTier": "Standard",
      "displayName": "Office 365 Users",
      "iconUri": "https://connectoricons-prod.azureedge.net/releases/v1.0.1717/1.0.1717.3929/office365users/icon.png",
      "id": "/providers/microsoft.powerapps/apis/shared_office365users",
      "parameterHints": {},
      "parameterHintsV2": {}
    },
    "datasets": {},
    "dataSources": [
      "Office365Users"
    ],
    "dependencies": {},
    "dependents": [],
    "id": "5afad8e3-abb9-4f2d-b8b5-fdb2e81b1583"
  },
  "5cf44127-903d-495d-8399-7aa53cd750c4": {
    "appActions": [],
    "connectionRef": {
      "apiTier": "Standard",
      "displayName": "Office 365 Outlook",
      "iconUri": "https://connectoricons-prod.azureedge.net/releases/v1.0.1716/1.0.1716.3922/office365/icon.png",
      "id": "/providers/microsoft.powerapps/apis/shared_office365",
      "parameterHints": {},
      "parameterHintsV2": {}
    },
    "datasets": {},
    "dataSources": [],
    "dependencies": {},
    "dependents": [
      "5da627cb-7ece-4c8a-8780-c2391ae7939d"
    ],
    "id": "5cf44127-903d-495d-8399-7aa53cd750c4"
  },
  "5da627cb-7ece-4c8a-8780-c2391ae7939d": {
    "appActions": [
      "Run"
    ],
    "connectionRef": {
      "apiTier": "Standard",
      "displayName": "Logic flows",
      "iconUri": "https://connectoricons-prod.azureedge.net/releases/v1.0.1719/1.0.1719.3955/logicflows/icon.png",
      "id": "/providers/microsoft.powerapps/apis/shared_logicflows",
      "parameterHints": {
        "362c4cb3-5166-4138-b723-445c14f85649": {
          "value": "shared_commondataserviceforapps_1"
        },
        "5cf44127-903d-495d-8399-7aa53cd750c4": {
          "value": "shared_office365"
        },
        "93812653-bb19-4e50-8255-dc1ee8bb91ba": {
          "value": "shared_approvals_1"
        },
        "workflowEntityId": {
          "value": "8e31165c-4769-ee11-9ae7-00224808117c"
        },
        "workflowName": {
          "value": "4b1190c3-13c4-4841-8299-a08e02cc1429"
        }
      },
      "parameterHintsV2": {
        "shared_approvals_1": {
          "value": "93812653-bb19-4e50-8255-dc1ee8bb91ba"
        },
        "shared_commondataserviceforapps": {
          "value": "362c4cb3-5166-4138-b723-445c14f85649"
        },
        "shared_commondataserviceforapps_1": {
          "value": "362c4cb3-5166-4138-b723-445c14f85649"
        },
        "shared_office365": {
          "value": "5cf44127-903d-495d-8399-7aa53cd750c4"
        },
        "workflowEntityId": {
          "value": "8e31165c-4769-ee11-9ae7-00224808117c"
        },
        "workflowName": {
          "value": "4b1190c3-13c4-4841-8299-a08e02cc1429"
        }
      }
    },
    "datasets": {},
    "dataSources": [
      "HardwareRequestSubmittedForApproval"
    ],
    "dependencies": {
      "shared_approvals_1": "93812653-bb19-4e50-8255-dc1ee8bb91ba",
      "shared_commondataserviceforapps": "362c4cb3-5166-4138-b723-445c14f85649",
      "shared_commondataserviceforapps_1": "362c4cb3-5166-4138-b723-445c14f85649",
      "shared_office365": "5cf44127-903d-495d-8399-7aa53cd750c4"
    },
    "dependents": [],
    "id": "5da627cb-7ece-4c8a-8780-c2391ae7939d"
  },
  "93812653-bb19-4e50-8255-dc1ee8bb91ba": {
    "appActions": [],
    "connectionRef": {
      "apiTier": "Standard",
      "displayName": "Approvals",
      "iconUri": "https://connectoricons-prod.azureedge.net/releases/v1.0.1719/1.0.1719.3952/approvals/icon.png",
      "id": "/providers/microsoft.powerapps/apis/shared_approvals",
      "parameterHints": {},
      "parameterHintsV2": {}
    },
    "datasets": {},
    "dataSources": [],
    "dependencies": {},
    "dependents": [
      "5da627cb-7ece-4c8a-8780-c2391ae7939d"
    ],
    "id": "93812653-bb19-4e50-8255-dc1ee8bb91ba"
  }
}